pdap_access_manager/__init__.py
pdap_access_manager/access_manager/__init__.py
pdap_access_manager/access_manager/_base.py
pdap_access_manager/access_manager/async_.py
pdap_access_manager/access_manager/sync.py
pdap_access_manager/constants.py
pdap_access_manager/enums.py
pdap_access_manager/exceptions.py
pdap_access_manager/helpers.py
pdap_access_manager/mappings.py
pdap_access_manager/models/__init__.py
pdap_access_manager/models/auth.py
pdap_access_manager/models/request.py
pdap_access_manager/models/response.py
pdap_access_manager/models/tokens.py
pdap_access_manager-0.4.4.dist-info/METADATA
pdap_access_manager-0.4.4.dist-info/WHEEL
pdap_access_manager-0.4.4.dist-info/licenses/LICENSE
pdap_access_manager-0.4.4.dist-info/RECORD
