Metadata-Version: 2.4
Name: pdap-access-manager
Version: 0.4.4
Summary: Access Manager for accessing PDAP API
License: MIT
License-File: LICENSE
Author: Max Chis
Author-email: maxachis@gmail.com
Requires-Python: >=3.11
Classifier: License :: OSI Approved :: MIT License
Classifier: Operating System :: OS Independent
Classifier: Programming Language :: Python :: 3
Classifier: Programming Language :: Python :: 3.11
Classifier: Programming Language :: Python :: 3.12
Classifier: Programming Language :: Python :: 3.13
Classifier: Programming Language :: Python :: 3.14
Requires-Dist: aiohttp (==3.11.18)
Requires-Dist: boltons (>=25.0.0,<26.0.0)
Requires-Dist: pydantic (==2.11.3)
Requires-Dist: requests (==2.32.3)
Project-URL: Documentation, https://github.com/Police-Data-Accessibility-Project/Access-Manager
Project-URL: Homepage, https://github.com/Police-Data-Accessibility-Project/Access-Manager
Project-URL: Issues, https://github.com/Police-Data-Accessibility-Project/Access-Manager/issues
Project-URL: Repository, https://github.com/Police-Data-Accessibility-Project/Access-Manager
